qiskit_qward-0.16.0.dist-info/licenses/LICENSE.txt
qward/VERSION.txt
qward/__init__.py
qward/scanner.py
qward/version.py
qward/algorithms/__init__.py
qward/algorithms/executor.py
qward/algorithms/grover.py
qward/algorithms/pvqd.py
qward/algorithms/qaoa.py
qward/algorithms/v_tp.py
qward/algorithms/vqte.py
qward/examples/__init__.py
qward/examples/aer.py
qward/examples/behavioral_visualizer_example.py
qward/examples/circuit_performance_demo.py
qward/examples/clean_teleportation_example.py
qward/examples/complexity_metrics_validation.py
qward/examples/comprehensive_example.py
qward/examples/direct_strategy_example.py
qward/examples/example_metrics_constructor.py
qward/examples/example_visualizer.py
qward/examples/executor_example.py
qward/examples/new_api_usage_example.py
qward/examples/quantum_specific_visualizer_example.py
qward/examples/qward_paper.py
qward/examples/qward_paper_grover.py
qward/examples/schema_demo.py
qward/examples/structural_visualizer_example.py
qward/examples/test_new_visualization_api.py
qward/examples/test_visualization_defaults.py
qward/examples/utils.py
qward/examples/visualization_demo.py
qward/examples/visualization_quickstart.py
qward/metrics/__init__.py
qward/metrics/base_metric.py
qward/metrics/behavioral_metrics.py
qward/metrics/circuit_performance.py
qward/metrics/complexity_metrics.py
qward/metrics/defaults.py
qward/metrics/element_metrics.py
qward/metrics/qiskit_metrics.py
qward/metrics/quantum_specific_metrics.py
qward/metrics/structural_metrics.py
qward/metrics/types.py
qward/schemas/behavioral_metrics_schema.py
qward/schemas/circuit_performance_schema.py
qward/schemas/complexity_metrics_schema.py
qward/schemas/element_metrics_schema.py
qward/schemas/legacy_schemas.py
qward/schemas/loc_metrics_schema.py
qward/schemas/qiskit_metrics_schema.py
qward/schemas/quantum_specific_metrics_schema.py
qward/schemas/structural_metrics_schema.py
qward/utils/__init__.py
qward/utils/flatten.py
qward/utils/metrics_executor.py
qward/visualization/__init__.py
qward/visualization/base.py
qiskit_qward-0.16.0.dist-info/METADATA
qiskit_qward-0.16.0.dist-info/WHEEL
qiskit_qward-0.16.0.dist-info/top_level.txt
qiskit_qward-0.16.0.dist-info/RECORD
