Metadata-Version: 2.4
Name: qiskit-qward
Version: 0.16.0
Summary: A framework for analyzing and validating quantum code execution quality on quantum processing units (QPUs)
Home-page: https://github.com/xthecapx/qiskit-qward
Author: Thecap
Author-email: xthecapx@gmail.com
License: Apache-2.0
Project-URL: Bug Tracker, https://github.com/xthecapx/qiskit-qward/issues
Project-URL: Documentation, https://xthecapx.github.io/qiskit-qward/
Project-URL: Source Code, https://github.com/xthecapx/qiskit-qward
Keywords: qiskit sdk quantum validation analysis metrics quality
Classifier: Environment :: Console
Classifier: Intended Audience :: Developers
Classifier: Intended Audience :: Science/Research
Classifier: Operating System :: Microsoft :: Windows
Classifier: Operating System :: MacOS
Classifier: Operating System :: POSIX :: Linux
Classifier: Programming Language :: Python :: 3 :: Only
Classifier: Programming Language :: Python :: 3.10
Classifier: Programming Language :: Python :: 3.11
Classifier: Programming Language :: Python :: 3.12
Classifier: Topic :: Scientific/Engineering
Requires-Python: >=3.10
License-File: LICENSE.txt
Requires-Dist: qiskit==2.1.2
Requires-Dist: qiskit-aer==0.17.1
Requires-Dist: qiskit-ibm-runtime==0.41.1
Requires-Dist: qbraid[braket]==0.9.8
Requires-Dist: numpy>=1.24.0
Requires-Dist: pandas>=2.0.0
Requires-Dist: matplotlib>=3.7.0
Requires-Dist: python-dotenv>=1.0.0
Requires-Dist: pylatexenc
Requires-Dist: ibm-cloud-sdk-core==3.24.1
Requires-Dist: ibm-platform-services==0.66.1
Requires-Dist: pydantic-settings
Requires-Dist: requests==2.32.3
Requires-Dist: dotenv
Requires-Dist: statsmodels
Requires-Dist: torch==2.8.0
Dynamic: author
Dynamic: author-email
Dynamic: classifier
Dynamic: description
Dynamic: description-content-type
Dynamic: home-page
Dynamic: keywords
Dynamic: license
Dynamic: license-file
Dynamic: project-url
Dynamic: requires-dist
Dynamic: requires-python
Dynamic: summary
